dql_core/__init__.py
dql_core/_version.py
dql_core/evaluator.py
dql_core/exceptions.py
dql_core/executor.py
dql_core/results.py
dql_core/adapters/__init__.py
dql_core/adapters/base.py
dql_core/adapters/factory.py
dql_core/adapters/rate_limiter.py
dql_core/adapters/retry.py
dql_core/cleaners/__init__.py
dql_core/cleaners/audit.py
dql_core/cleaners/base.py
dql_core/cleaners/chain.py
dql_core/cleaners/data_type_cleaners.py
dql_core/cleaners/decorators.py
dql_core/cleaners/discovery.py
dql_core/cleaners/registry.py
dql_core/cleaners/string_cleaners.py
dql_core/cleaners/transaction.py
dql_core/cleaners/validation.py
dql_core/validators/__init__.py
dql_core/validators/base.py
dql_core/validators/comparison_validators.py
dql_core/validators/custom_validators.py
dql_core/validators/enum_validators.py
dql_core/validators/length_validators.py
dql_core/validators/null_validators.py
dql_core/validators/pattern_validators.py
dql_core/validators/range_validators.py
dql_core/validators/reference_validators.py
dql_core/validators/registry.py
dql_core/validators/uniqueness_validators.py
dql_core-0.5.2.dist-info/licenses/LICENSE
dql_core-0.5.2.dist-info/METADATA
dql_core-0.5.2.dist-info/WHEEL
dql_core-0.5.2.dist-info/top_level.txt
dql_core-0.5.2.dist-info/RECORD
