Metadata-Version: 2.4
Name: dql-core
Version: 0.5.2
Summary: Framework-agnostic validation engine for Data Quality Language (DQL)
Author-email: "stratege.ai Team" <info@stragete.ai>
License: MIT
Project-URL: Homepage, https://stratege.ai/tools/dql-core
Project-URL: Documentation, https://dql-core.readthedocs.io
Project-URL: Repository, https://github.com/stratege.ai/dql-core
Project-URL: Issues, https://github.com/stratege.ai/dql-core/issues
Project-URL: Changelog, https://github.com/stratege.ai/dql-core/blob/main/CHANGELOG.md
Keywords: dql,validation,data-quality,framework-agnostic
Classifier: Development Status :: 3 - Alpha
Classifier: Intended Audience :: Developers
Classifier: License :: OSI Approved :: MIT License
Classifier: Programming Language :: Python :: 3
Classifier: Programming Language :: Python :: 3.8
Classifier: Programming Language :: Python :: 3.9
Classifier: Programming Language :: Python :: 3.10
Classifier: Programming Language :: Python :: 3.11
Classifier: Programming Language :: Python :: 3.12
Requires-Python: >=3.8
License-File: LICENSE
Requires-Dist: dql-parser<1.0.0,>=0.1.1
Provides-Extra: external-apis
Requires-Dist: requests>=2.28.0; extra == "external-apis"
Requires-Dist: tenacity>=8.0.0; extra == "external-apis"
Provides-Extra: dev
Requires-Dist: pytest>=7.0; extra == "dev"
Requires-Dist: pytest-cov>=4.0; extra == "dev"
Requires-Dist: pytest-mock>=3.10; extra == "dev"
Requires-Dist: black>=23.0; extra == "dev"
Requires-Dist: flake8>=6.0; extra == "dev"
Requires-Dist: mypy>=1.0; extra == "dev"
Dynamic: license-file
